igblast_parser/__init__.py
igblast_parser/module1.cpython-39-darwin.so
igblast_parser-0.0.4.data/scripts/igblast-parser
igblast_parser-0.0.4.dist-info/LICENSE
igblast_parser-0.0.4.dist-info/METADATA
igblast_parser-0.0.4.dist-info/WHEEL
igblast_parser-0.0.4.dist-info/top_level.txt
igblast_parser-0.0.4.dist-info/RECORD
