Metadata-Version: 2.1
Name: igblast-parser
Version: 0.0.4
Summary: Parser of Igblast results into a csv file
Home-page: https://github.com/aerijman/igblast-parser
Author: Ariel Erijman & Brad Langhorst
Author-email: aerijman@fredhutch.org
License: UNKNOWN
Platform: UNKNOWN
Requires-Python: >=3.6
Requires-Dist: pandas
Requires-Dist: numpy
